vcolorpicker/__init__.py
vcolorpicker/__main__.py
vcolorpicker/img.py
vcolorpicker/ui_dark.py
vcolorpicker/ui_dark_alpha.py
vcolorpicker/ui_light.py
vcolorpicker/ui_light_alpha.py
vcolorpicker/vcolorpicker.py
vcolorpicker-1.4.4.dist-info/LICENSE
vcolorpicker-1.4.4.dist-info/METADATA
vcolorpicker-1.4.4.dist-info/WHEEL
vcolorpicker-1.4.4.dist-info/top_level.txt
vcolorpicker-1.4.4.dist-info/RECORD
