Metadata-Version: 2.1
Name: vcolorpicker
Version: 1.4.4
Summary: Open a visual vcolorpicker from any project.
Home-page: https://github.com/nlfmt/pyqt-colorpicker
Author: nlfmt
Author-email: nlfmt@gmx.de
License: MIT
Project-URL: GitHub, https://github.com/nlfmt/pyqt-colorpicker
Project-URL: Bug Tracker, https://github.com/nlfmt/pyqt-colorpicker/issues
Keywords: python color gui colorpicker visual qt
Classifier: Development Status :: 5 - Production/Stable
Classifier: Environment :: MacOS X
Classifier: Environment :: Win32 (MS Windows)
Classifier: Environment :: X11 Applications :: Qt
Classifier: Intended Audience :: Developers
Classifier: License :: OSI Approved :: MIT License
Classifier: Operating System :: OS Independent
Classifier: Programming Language :: Python :: 3
Classifier: Programming Language :: Python :: 3 :: Only
Classifier: Topic :: Software Development :: Libraries
Classifier: Topic :: Software Development :: User Interfaces
Classifier: Topic :: Software Development :: Widget Sets
Requires-Python: >=3.7
License-File: LICENSE
Requires-Dist: qtpy
